tufte/__init__.py
tufte/bar.py
tufte/base.py
tufte/box.py
tufte/line.py
tufte/scatter.py
tufte/tufte.py
tufte-0.2.3.dist-info/LICENSE.md
tufte-0.2.3.dist-info/WHEEL
tufte-0.2.3.dist-info/METADATA
tufte-0.2.3.dist-info/RECORD
